django_htmx_ui_adminlte/__init__.py
django_htmx_ui_adminlte/admin.py
django_htmx_ui_adminlte/apps.py
django_htmx_ui_adminlte/forms.py
django_htmx_ui_adminlte/models.py
django_htmx_ui_adminlte/tests.py
django_htmx_ui_adminlte/urls.py
django_htmx_ui_adminlte/utils.py
django_htmx_ui_adminlte/widgets.py
django_htmx_ui_adminlte/migrations/__init__.py
django_htmx_ui_adminlte/views/dashboard.py
django_htmx_ui_adminlte/views/errors.py
django_htmx_ui_adminlte/views/panel.py
django_htmx_ui_adminlte/views/users.py
django_htmx_ui_adminlte/views/welcome.py
django_htmx_ui_adminlte-0.1.5.dist-info/LICENSE
django_htmx_ui_adminlte-0.1.5.dist-info/METADATA
django_htmx_ui_adminlte-0.1.5.dist-info/WHEEL
django_htmx_ui_adminlte-0.1.5.dist-info/top_level.txt
django_htmx_ui_adminlte-0.1.5.dist-info/RECORD
