Metadata-Version: 2.1
Name: django-htmx-ui-adminlte
Version: 0.1.5
Summary: AdminLTE - Django - HTMX - Jinja powerful combination library
Author-email: Nikalexis Nikolaos <nikalexis@gmail.com>
Project-URL: Homepage, https://github.com/nikalexis/django_htmx_ui_adminlte
Project-URL: Bug Tracker, https://github.com/nikalexis/django_htmx_ui_adminlte/issues
Classifier: Programming Language :: Python :: 3
Classifier: License :: OSI Approved :: MIT License
Classifier: Operating System :: OS Independent
Requires-Python: >=3.11
License-File: LICENSE
Requires-Dist: Django (>=4.1.0)
Requires-Dist: django-htmx-ui (>=0.1.3)
